nhc2_coco/__init__.py
nhc2_coco/coco.py
nhc2_coco/coco_ca.pem
nhc2_coco/coco_climate.py
nhc2_coco/coco_device_class.py
nhc2_coco/coco_discover.py
nhc2_coco/coco_discover_profiles.py
nhc2_coco/coco_entity.py
nhc2_coco/coco_fan.py
nhc2_coco/coco_fan_speed.py
nhc2_coco/coco_generic.py
nhc2_coco/coco_light.py
nhc2_coco/coco_login_validation.py
nhc2_coco/coco_profiles.py
nhc2_coco/coco_shutter.py
nhc2_coco/coco_switch.py
nhc2_coco/coco_switched_fan.py
nhc2_coco/const.py
nhc2_coco/helpers.py
nhc2_coco/tests/credentials_example.py
nhc2_coco/tests/discover_profiles.py
nhc2_coco/tests/discover_profiles_by_host.py
nhc2_coco/tests/test_example.py
nhc2_coco-1.4.1.dist-info/LICENSE
nhc2_coco-1.4.1.dist-info/WHEEL
nhc2_coco-1.4.1.dist-info/METADATA
nhc2_coco-1.4.1.dist-info/RECORD
